{
    "id": "roundcube-email-and-contacts",
    "name": "Roundcube Email And Contacts",
    "description": "Email and Contacts module for Spaces & Users.",
    "keywords": [
        "Email",
        "Contacts",
        "Roundcube"
    ],
    "version": "1.1",
    "humhub": {
        "minVersion": "1.6"
    },
    "homepage": "https://github.com/olantrust/humhub-roundcube",
    "authors": [
        {
            "name": "Storm Poorun"
        },
        {
            "name": "Vijay Padhariya"
        }
    ],
    "screenshots": [
        "resources/screenshot-1.png",
        "resources/screenshot-2.png",
        "resources/screenshot-3.png",
        "resources/screenshot-4.png",
        "resources/screenshot-5.png"
    ]
}